cnnutils.py
cnnutils/cnnutils.py
cnnutils-0.0.1.dist-info/METADATA
cnnutils-0.0.1.dist-info/WHEEL
cnnutils-0.0.1.dist-info/top_level.txt
cnnutils-0.0.1.dist-info/RECORD
