Metadata-Version: 2.1
Name: cnnutils
Version: 0.0.1
Summary: A set of utility function which help build convolutional neural networks
Home-page: https://github.com/igor97100/cnnutils
Author: Igor Spiridonov
Author-email: igor.spiridonov@protonmail.com
License: MIT
Download-URL: https://github.com/igor97100/cnnutils/archive/v_01.tar.gz
Keywords: cnn,convolutional,neural network,convolution
Platform: UNKNOWN
